mvmake/__init__.py
mvmake/__main__.py
mvmake/sourceclip.py
mvmake/videosize.py
mvmake-1.0.0.dist-info/LICENSE
mvmake-1.0.0.dist-info/METADATA
mvmake-1.0.0.dist-info/WHEEL
mvmake-1.0.0.dist-info/entry_points.txt
mvmake-1.0.0.dist-info/top_level.txt
mvmake-1.0.0.dist-info/RECORD
