Metadata-Version: 2.1
Name: mvmake
Version: 1.0.0
Summary: A script to cut a directory of clips to music.
Home-page: https://github.com/kenyerman/mvmake
Author: kenyerman
License: UNKNOWN
Project-URL: Bug Tracker, https://github.com/kenyerman/mvmake/issues
Platform: UNKNOWN
Classifier: Programming Language :: Python :: 3.7
Classifier: License :: OSI Approved :: MIT License
Classifier: Operating System :: OS Independent
Requires-Python: >=3.7
License-File: LICENSE
Requires-Dist: tqdm
Requires-Dist: librosa
Requires-Dist: moviepy
